sshcld/__init__.py
sshcld/cli.py
sshcld/errors.py
sshcld/sshcld.yaml
sshcld/plugins/__init__.py
sshcld/plugins/aws.py
sshcld-0.0.3.dist-info/LICENSE
sshcld-0.0.3.dist-info/METADATA
sshcld-0.0.3.dist-info/WHEEL
sshcld-0.0.3.dist-info/entry_points.txt
sshcld-0.0.3.dist-info/top_level.txt
sshcld-0.0.3.dist-info/RECORD
