Metadata-Version: 2.1
Name: sshcld
Version: 0.0.3
Summary: Get cloud servers list for your SSH client
Home-page: https://github.com/sergey-trukhin/sshcld
Author: Sergey Trukhin
Author-email: satruhin@gmail.com
License: MIT
Keywords: SSH,cloud,AWS
Platform: any
Classifier: Development Status :: 3 - Alpha
Classifier: Intended Audience :: System Administrators
Classifier: License :: OSI Approved :: MIT License
Classifier: Programming Language :: Python
Classifier: Programming Language :: Python :: 3.5
Classifier: Programming Language :: Python :: 3.6
Classifier: Programming Language :: Python :: 3.7
Classifier: Programming Language :: Python :: 3.8
Classifier: Programming Language :: Python :: 3.9
Classifier: Programming Language :: Python :: 3.10
Classifier: Topic :: System :: Systems Administration
Classifier: Operating System :: OS Independent
Requires-Python: >=3.5
License-File: LICENSE
Requires-Dist: boto3
Requires-Dist: botocore
Requires-Dist: PyYAML
Requires-Dist: tabulate
